{
  "timestamp": "2025-06-24T13:17:09.970591+09:00",
  "data_time": "2025-06-24T13:10:00+09:00",
  "dam": {
    "water_level": 36.77,
    "storage_rate": 97.4,
    "inflow": 38.99,
    "outflow": 34.1,
    "storage_change": null
  },
  "river": {
    "water_level": 3.04,
    "level_change": 0.0,
    "status": "正常"
  },
  "rainfall": {
    "hourly": 0,
    "cumulative": 0,
    "change": 0
  },
  "weather": {
    "today": {
      "weather_code": "302",
      "weather_text": "雨　時々　くもり　所により　雷　を伴う",
      "temp_max": 27,
      "temp_min": 27,
      "precipitation_probability": [
        80,
        80
      ],
      "precipitation_times": [
        "12時",
        "18時"
      ]
    },
    "tomorrow": {
      "weather_code": "203",
      "weather_text": "くもり　時々　雨　所により　雷　を伴う",
      "temp_max": 29,
      "temp_min": 25,
      "precipitation_probability": [
        70,
        40,
        50,
        70
      ],
      "precipitation_times": [
        "00時",
        "06時",
        "12時",
        "18時"
      ]
    },
    "day_after_tomorrow": {
      "weather_code": "202",
      "weather_text": "くもり一時雨",
      "temp_max": null,
      "temp_min": null,
      "precipitation_probability": [
        60
      ],
      "precipitation_times": [
        "日中"
      ]
    },
    "update_time": "2025-06-24T11:00:00+09:00",
    "weekly_forecast": [
      {
        "date": "2025-06-25",
        "day_of_week": "Wed",
        "weather_code": "203",
        "weather_text": "くもり時々雨",
        "precipitation_probability": null
      },
      {
        "date": "2025-06-26",
        "day_of_week": "Thu",
        "weather_code": "202",
        "weather_text": "くもり一時雨",
        "precipitation_probability": 60
      },
      {
        "date": "2025-06-27",
        "day_of_week": "Fri",
        "weather_code": "201",
        "weather_text": "くもり時々晴れ",
        "precipitation_probability": 30
      },
      {
        "date": "2025-06-28",
        "day_of_week": "Sat",
        "weather_code": "101",
        "weather_text": "晴れ時々くもり",
        "precipitation_probability": 30
      },
      {
        "date": "2025-06-29",
        "day_of_week": "Sun",
        "weather_code": "101",
        "weather_text": "晴れ時々くもり",
        "precipitation_probability": 30
      },
      {
        "date": "2025-06-30",
        "day_of_week": "Mon",
        "weather_code": "101",
        "weather_text": "晴れ時々くもり",
        "precipitation_probability": 30
      },
      {
        "date": "2025-07-01",
        "day_of_week": "Tue",
        "weather_code": "101",
        "weather_text": "晴れ時々くもり",
        "precipitation_probability": 30
      }
    ]
  }
}